AUTHORS.rst
CONTRIBUTING.rst
HISTORY.rst
LICENSE
MANIFEST.in
README.rst
setup.cfg
setup.py
dj_mypypi.egg-info/PKG-INFO
dj_mypypi.egg-info/SOURCES.txt
dj_mypypi.egg-info/dependency_links.txt
dj_mypypi.egg-info/not-zip-safe
dj_mypypi.egg-info/top_level.txt
djmypypi/__init__.py
djmypypi/admin.py
djmypypi/apps.py
djmypypi/models.py
djmypypi/urls.py
djmypypi/views.py
djmypypi/migrations/0001_initial.py
djmypypi/migrations/__init__.py
djmypypi/static/css/djmypypi.css
djmypypi/static/js/djmypypi.js
djmypypi/templates/djmypypi/base.html
djmypypi/templates/djmypypi/index.html
djmypypi/templates/djmypypi/package.html
djmypypi/test_utils/__init__.py
djmypypi/test_utils/test_app/__init__.py
djmypypi/test_utils/test_app/admin.py
djmypypi/test_utils/test_app/apps.py
djmypypi/test_utils/test_app/models.py
djmypypi/test_utils/test_app/migrations/__init__.py