Metadata-Version: 1.1
Name: dj-mypypi
Version: 0.1.0
Summary: This package provides a private python package index based on django
Home-page: https://github.com/kverdecia/dj-mypypi
Author: Karel Antonio Verdecia Ortiz
Author-email: kverdecia@gmail.com
License: MIT
Keywords: dj-mypypi
Platform: UNKNOWN
Classifier: Development Status :: 3 - Alpha
Classifier: Framework :: Django :: 2.1
Classifier: Framework :: Django :: 3.0
Classifier: Intended Audience :: Developers
Classifier: License :: OSI Approved :: BSD License
Classifier: Natural Language :: English
Classifier: Programming Language :: Python :: 3
Classifier: Programming Language :: Python :: 3.5
Classifier: Programming Language :: Python :: 3.6
Classifier: Programming Language :: Python :: 3.7
Classifier: Programming Language :: Python :: 3.8
